encrypted_stream.py
encrypted_stream-0.1a1.dist-info/DESCRIPTION.rst
encrypted_stream-0.1a1.dist-info/METADATA
encrypted_stream-0.1a1.dist-info/RECORD
encrypted_stream-0.1a1.dist-info/WHEEL
encrypted_stream-0.1a1.dist-info/metadata.json
encrypted_stream-0.1a1.dist-info/top_level.txt
