Metadata-Version: 2.0
Name: encrypted-stream
Version: 0.1a1
Summary: Transparent encryption and decryption for file-like objects
Home-page: https://github.com/antoniusf/encrypted-stream
Author: Antonius Frie
Author-email: antonius.frie@ruhr-uni-bochum.de
License: Apache Software License
Platform: UNKNOWN
Classifier: Development Status :: 3 - Alpha
Classifier: Topic :: Security :: Cryptography
Classifier: License :: OSI Approved :: Apache Software License
Classifier: Programming Language :: Python :: 3
Requires-Dist: pynacl (>=1.3)
